mypylib/MP_shioaji_ticks.py
mypylib/__init__.py
mypylib/binance.py
mypylib/binance_copy_bot.py
mypylib/chdbif.py
mypylib/crawler.py
mypylib/crypto.py
mypylib/daily_routine.py
mypylib/finmind.py
mypylib/keys.py
mypylib/libexcel.py
mypylib/multicast_quote.py
mypylib/mvp.py
mypylib/my_random_proxy.py
mypylib/myemail.py
mypylib/option_test.py
mypylib/put2.py
mypylib/rayin.py
mypylib/redisconnectionmanager.py
mypylib/shioaji_history_ticks.py
mypylib/shioaji_kline.py
mypylib/shioaji_ticks.py
mypylib/sjtools.py
mypylib/tLineNotify.py
mypylib/ti.py
mypylib/ticks_downloader.py
mypylib/tplaysound.py
mypylib/tredis.py
mypylib/warrant.py
mypylib/quote_module/__init__.py
mypylib/quote_module/test.py
mypylib/tmpDevelopment/__init__.py
mypylib/tmpDevelopment/warrant_test.py
mypylib-0.2.74.dist-info/METADATA
mypylib-0.2.74.dist-info/WHEEL
mypylib-0.2.74.dist-info/top_level.txt
mypylib-0.2.74.dist-info/RECORD
