Metadata-Version: 2.4
Name: mypylib
Version: 0.2.74
Summary: Your package description
Home-page: https://github.com/williamchen180/mypylib
Author: William Chen
Author-email: williamchen180@gmail.com
Classifier: Programming Language :: Python :: 3
Classifier: License :: OSI Approved :: MIT License
Classifier: Operating System :: OS Independent
Requires-Dist: pandas
Requires-Dist: termcolor
Requires-Dist: requests
Requires-Dist: plotly
Requires-Dist: setuptools
Requires-Dist: matplotlib
Requires-Dist: numpy
Requires-Dist: playsound
Requires-Dist: wheel
Requires-Dist: twine
Requires-Dist: cryptocode
Requires-Dist: line_notify
Requires-Dist: shioaji
Requires-Dist: pandasql
Requires-Dist: msgpack
Requires-Dist: xlrd
Requires-Dist: lxml
Dynamic: author
Dynamic: author-email
Dynamic: classifier
Dynamic: description
Dynamic: description-content-type
Dynamic: home-page
Dynamic: requires-dist
Dynamic: summary
